LICENSE
MANIFEST.in
README.md
setup.py
serrano/__init__.py
serrano/admin.py
serrano/backends.py
serrano/cors.py
serrano/formatters.py
serrano/forms.py
serrano/links.py
serrano/middleware.py
serrano/models.py
serrano/tokens.py
serrano/urls.py
serrano/utils.py
serrano.egg-info/PKG-INFO
serrano.egg-info/SOURCES.txt
serrano.egg-info/dependency_links.txt
serrano.egg-info/pbr.json
serrano.egg-info/requires.txt
serrano.egg-info/top_level.txt
serrano/conf/__init__.py
serrano/conf/global_settings.py
serrano/migrations/0001_initial.py
serrano/migrations/__init__.py
serrano/resources/__init__.py
serrano/resources/base.py
serrano/resources/category.py
serrano/resources/concept.py
serrano/resources/context.py
serrano/resources/exporter.py
serrano/resources/history.py
serrano/resources/jobs.py
serrano/resources/pagination.py
serrano/resources/preview.py
serrano/resources/processors.py
serrano/resources/sets.py
serrano/resources/stats.py
serrano/resources/templates.py
serrano/resources/view.py
serrano/resources/async/__init__.py
serrano/resources/async/exporter.py
serrano/resources/async/preview.py
serrano/resources/async/query.py
serrano/resources/field/__init__.py
serrano/resources/field/base.py
serrano/resources/field/dims.py
serrano/resources/field/dist.py
serrano/resources/field/stats.py
serrano/resources/field/values.py
serrano/resources/query/__init__.py
serrano/resources/query/base.py
serrano/resources/query/forks.py
serrano/resources/query/results.py
serrano/resources/query/stats.py