Metadata-Version: 1.1
Name: serrano
Version: 2.4.4
Summary: Hypermedia implementation for Avocado
Home-page: http://github.com/cbmi/serrano
Author: Byron Ruth
Author-email: b@devel.io
License: BSD
Keywords: hypermedia rest api avocado serrano cilantro harvest
Platform: UNKNOWN
Classifier: Development Status :: 5 - Production/Stable
Classifier: License :: OSI Approved :: BSD License
Classifier: Programming Language :: Python :: 2.6
Classifier: Programming Language :: Python :: 2.7
Classifier: Framework :: Django
Classifier: Topic :: Internet :: WWW/HTTP
Classifier: Intended Audience :: Developers
Classifier: Intended Audience :: Science/Research
Classifier: Intended Audience :: Healthcare Industry
Classifier: Intended Audience :: Information Technology
